Workbook

Sheet retail_store_sales
A1: Transaction ID | B1: Customer ID | C1: Category | D1: Item | E1: Price Per Unit | F1: Quantity | G1: Total Spent | H1: Payment Method | I1: Location | J1: Transaction Date | K1: Discount Applied | L1: Category Code | M1: ITEM_ID | N1: PRODUCT_NAME | O1: STOCK_LEVELS | P1: DISCOUNT_AMT | Q1: DISCOUNT_PERCENT
A2: TXN_6867343 | B2: CUST_09 | C2: Patisserie | D2: Item_10_PAT | E2: 18.5 | F2: 10 | G2: 185 | H2: Digital Wallet | I2: Online | J2: 45390 | K2: =TRUE() -> TRUE | L2: =IFERROR(INDEX(CategoryCodes!$B$2:$B$9,MATCH(C2,CategoryCodes!$A$2:$A$9,0)),"") -> H | M2: =IFERROR(VALUE(MID(D2,FIND("_",D2)+1,FIND("_",D2,FIND("_",D2)+1)-FIND("_",D2)-1)),"") -> 10 | N2: =IF(OR(C2="",M2=""),"",C2&" Item "&M2) -> Patisserie Item 10 | O2: 327 | P2: =G2*Q2 -> 18.5 | Q2: =IF(K2=TRUE(),0.1,0) -> 0.1
A3: TXN_3731986 | B3: CUST_22 | C3: Milk Products | D3: Item_17_MILK | E3: 29 | F3: 9 | G3: 261 | H3: Digital Wallet | I3: Online | J3: 45130 | K3: =TRUE() -> TRUE | L3: =IFERROR(INDEX(CategoryCodes!$B$2:$B$9,MATCH(C3,CategoryCodes!$A$2:$A$9,0)),"") -> G | M3: =IFERROR(VALUE(MID(D3,FIND("_",D3)+1,FIND("_",D3,FIND("_",D3)+1)-FIND("_",D3)-1)),"") -> 17 | N3: =IF(OR(C3="",M3=""),"",C3&" Item "&M3) -> Milk Products Item 17 | O3: 57 | P3: =G3*Q3 -> 26.1 | Q3: =IF(K3=TRUE(),0.1,0) -> 0.1
A4: TXN_9303719 | B4: CUST_02 | C4: Butchers | D4: Item_12_BUT | E4: 21.5 | F4: 2 | G4: 43 | H4: Credit Card | I4: Online | J4: 44839 | K4: =FALSE() -> FALSE | L4: =IFERROR(INDEX(CategoryCodes!$B$2:$B$9,MATCH(C4,CategoryCodes!$A$2:$A$9,0)),"") -> B | M4: =IFERROR(VALUE(MID(D4,FIND("_",D4)+1,FIND("_",D4,FIND("_",D4)+1)-FIND("_",D4)-1)),"") -> 12 | N4: =IF(OR(C4="",M4=""),"",C4&" Item "&M4) -> Butchers Item 12 | O4: 12 | P4: =G4*Q4 -> 0 | Q4: =IF(K4=TRUE(),0.1,0) -> 0
A5: TXN_9458126 | B5: CUST_06 | C5: Beverages | D5: Item_16_BEV | E5: 27.5 | F5: 9 | G5: 247.5 | H5: Credit Card | I5: Online | J5: 44688 | L5: =IFERROR(INDEX(CategoryCodes!$B$2:$B$9,MATCH(C5,CategoryCodes!$A$2:$A$9,0)),"") -> A | M5: =IFERROR(VALUE(MID(D5,FIND("_",D5)+1,FIND("_",D5,FIND("_",D5)+1)-FIND("_",D5)-1)),"") -> 16 | N5: =IF(OR(C5="",M5=""),"",C5&" Item "&M5) -> Beverages Item 16 | O5: 379 | P5: =G5*Q5 -> 0 | Q5: =IF(K5=TRUE(),0.1,0) -> 0
A6: TXN_4575373 | B6: CUST_05 | C6: Food | D6: Item_6_FOOD | E6: 12.5 | F6: 7 | G6: 87.5 | H6: Digital Wallet | I6: Online | J6: 44836 | K6: =FALSE() -> FALSE | L6: =IFERROR(INDEX(CategoryCodes!$B$2:$B$9,MATCH(C6,CategoryCodes!$A$2:$A$9,0)),"") -> E | M6: =IFERROR(VALUE(MID(D6,FIND("_",D6)+1,FIND("_",D6,FIND("_",D6)+1)-FIND("_",D6)-1)),"") -> 6 | N6: =IF(OR(C6="",M6=""),"",C6&" Item "&M6) -> Food Item 6 | O6: 140 | P6: =G6*Q6 -> 0 | Q6: =IF(K6=TRUE(),0.1,0) -> 0
A7: TXN_7482416 | B7: CUST_09 | C7: Patisserie | F7: 10 | G7: 200 | H7: Credit Card | I7: Online | J7: 45260 | L7: =IFERROR(INDEX(CategoryCodes!$B$2:$B$9,MATCH(C7,CategoryCodes!$A$2:$A$9,0)),"") -> H | M7: =IFERROR(VALUE(MID(D7,FIND("_",D7)+1,FIND("_",D7,FIND("_",D7)+1)-FIND("_",D7)-1)),"") | N7: =IF(OR(C7="",M7=""),"",C7&" Item "&M7) | O7: 125 | P7: =G7*Q7 -> 0 | Q7: =IF(K7=TRUE(),0.1,0) -> 0
A8: TXN_3652209 | B8: CUST_07 | C8: Food | D8: Item_1_FOOD | E8: 5 | F8: 8 | G8: 40 | H8: Credit Card | I8: In-store | J8: 45087 | K8: =TRUE() -> TRUE | L8: =IFERROR(INDEX(CategoryCodes!$B$2:$B$9,MATCH(C8,CategoryCodes!$A$2:$A$9,0)),"") -> E | M8: =IFERROR(VALUE(MID(D8,FIND("_",D8)+1,FIND("_",D8,FIND("_",D8)+1)-FIND("_",D8)-1)),"") -> 1 | N8: =IF(OR(C8="",M8=""),"",C8&" Item "&M8) -> Food Item 1 | O8: 114 | P8: =G8*Q8 -> 4 | Q8: =IF(K8=TRUE(),0.1,0) -> 0.1
A9: TXN_1372952 | B9: CUST_21 | C9: Furniture | E9: 33.5 | H9: Digital Wallet | I9: In-store | J9: 45384 | K9: =TRUE() -> TRUE | L9: =IFERROR(INDEX(CategoryCodes!$B$2:$B$9,MATCH(C9,CategoryCodes!$A$2:$A$9,0)),"") -> F | M9: =IFERROR(VALUE(MID(D9,FIND("_",D9)+1,FIND("_",D9,FIND("_",D9)+1)-FIND("_",D9)-1)),"") | N9: =IF(OR(C9="",M9=""),"",C9&" Item "&M9) | O9: 71 | P9: =G9*Q9 -> 0 | Q9: =IF(K9=TRUE(),0.1,0) -> 0.1
A10: TXN_9728486 | B10: CUST_23 | C10: Furniture | D10: Item_16_FUR | E10: 27.5 | F10: 1 | G10: 27.5 | H10: Credit Card | I10: In-store | J10: 45042 | K10: =FALSE() -> FALSE | L10: =IFERROR(INDEX(CategoryCodes!$B$2:$B$9,MATCH(C10,CategoryCodes!$A$2:$A$9,0)),"") -> F | M10: =IFERROR(VALUE(MID(D10,FIND("_",D10)+1,FIND("_",D10,FIND("_",D10)+1)-FIND("_",D10)-1)),"") -> 16 | N10: =IF(OR(C10="",M10=""),"",C10&" Item "&M10) -> Furniture Item 16 | O10: 377 | P10: =G10*Q10 -> 0 | Q10: =IF(K10=TRUE(),0.1,0) -> 0
A11: TXN_2722661 | B11: CUST_25 | C11: Butchers | D11: Item_22_BUT | E11: 36.5 | F11: 3 | G11: 109.5 | H11: Cash | I11: Online | J11: 45365 | K11: =FALSE() -> FALSE | L11: =IFERROR(INDEX(CategoryCodes!$B$2:$B$9,MATCH(C11,CategoryCodes!$A$2:$A$9,0)),"") -> B | M11: =IFERROR(VALUE(MID(D11,FIND("_",D11)+1,FIND("_",D11,FIND("_",D11)+1)-FIND("_",D11)-1)),"") -> 22 | N11: =IF(OR(C11="",M11=""),"",C11&" Item "&M11) -> Butchers Item 22 | O11: 52 | P11: =G11*Q11 -> 0 | Q11: =IF(K11=TRUE(),0.1,0) -> 0
A12: TXN_8776416 | B12: CUST_22 | C12: Butchers | D12: Item_3_BUT | E12: 8 | F12: 9 | G12: 72 | H12: Cash | I12: In-store | J12: 45640 | K12: =TRUE() -> TRUE | L12: =IFERROR(INDEX(CategoryCodes!$B$2:$B$9,MATCH(C12,CategoryCodes!$A$2:$A$9,0)),"") -> B | M12: =IFERROR(VALUE(MID(D12,FIND("_",D12)+1,FIND("_",D12,FIND("_",D12)+1)-FIND("_",D12)-1)),"") -> 3 | N12: =IF(OR(C12="",M12=""),"",C12&" Item "&M12) -> Butchers Item 3 | O12: 346 | P12: =G12*Q12 -> 7.2 | Q12: =IF(K12=TRUE(),0.1,0) -> 0.1
A13: TXN_5422631 | B13: CUST_09 | C13: Milk Products | F13: 8 | G13: 52 | H13: Digital Wallet | I13: In-store | J13: 45669 | K13: =TRUE() -> TRUE | L13: =IFERROR(INDEX(CategoryCodes!$B$2:$B$9,MATCH(C13,CategoryCodes!$A$2:$A$9,0)),"") -> G | M13: =IFERROR(VALUE(MID(D13,FIND("_",D13)+1,FIND("_",D13,FIND("_",D13)+1)-FIND("_",D13)-1)),"") | N13: =IF(OR(C13="",M13=""),"",C13&" Item "&M13) | O13: 379 | P13: =G13*Q13 -> 5.2 | Q13: =IF(K13=TRUE(),0.1,0) -> 0.1
A14: TXN_5874772 | B14: CUST_23 | C14: Food | D14: Item_2_FOOD | E14: 6.5 | F14: 7 | G14: 45.5 | H14: Cash | I14: Online | J14: 45178 | K14: =TRUE() -> TRUE | L14: =IFERROR(INDEX(CategoryCodes!$B$2:$B$9,MATCH(C14,CategoryCodes!$A$2:$A$9,0)),"") -> E | M14: =IFERROR(VALUE(MID(D14,FIND("_",D14)+1,FIND("_",D14,FIND("_",D14)+1)-FIND("_",D14)-1)),"") -> 2 | N14: =IF(OR(C14="",M14=""),"",C14&" Item "&M14) -> Food Item 2 | O14: 456 | P14: =G14*Q14 -> 4.55 | Q14: =IF(K14=TRUE(),0.1,0) -> 0.1
A15: TXN_4413070 | B15: CUST_14 | C15: Patisserie | D15: Item_24_PAT | E15: 39.5 | F15: 6 | G15: 237 | H15: Digital Wallet | I15: In-store | J15: 44701 | K15: =FALSE() -> FALSE | L15: =IFERROR(INDEX(CategoryCodes!$B$2:$B$9,MATCH(C15,CategoryCodes!$A$2:$A$9,0)),"") -> H | M15: =IFERROR(VALUE(MID(D15,FIND("_",D15)+1,FIND("_",D15,FIND("_",D15)+1)-FIND("_",D15)-1)),"") -> 24 | N15: =IF(OR(C15="",M15=""),"",C15&" Item "&M15) -> Patisserie Item 24 | O15: 279 | P15: =G15*Q15 -> 0 | Q15: =IF(K15=TRUE(),0.1,0) -> 0
A16: TXN_2490363 | B16: CUST_09 | C16: Milk Products | D16: Item_16_MILK | E16: 27.5 | F16: 2 | G16: 55 | H16: Digital Wallet | I16: Online | J16: 44703 | L16: =IFERROR(INDEX(CategoryCodes!$B$2:$B$9,MATCH(C16,CategoryCodes!$A$2:$A$9,0)),"") -> G | M16: =IFERROR(VALUE(MID(D16,FIND("_",D16)+1,FIND("_",D16,FIND("_",D16)+1)-FIND("_",D16)-1)),"") -> 16 | N16: =IF(OR(C16="",M16=""),"",C16&" Item "&M16) -> Milk Products Item 16 | O16: 44 | P16: =G16*Q16 -> 0 | Q16: =IF(K16=TRUE(),0.1,0) -> 0
A17: TXN_1809665 | B17: CUST_14 | C17: Beverages | E17: 24.5 | H17: Credit Card | I17: In-store | J17: 44692 | L17: =IFERROR(INDEX(CategoryCodes!$B$2:$B$9,MATCH(C17,CategoryCodes!$A$2:$A$9,0)),"") -> A | M17: =IFERROR(VALUE(MID(D17,FIND("_",D17)+1,FIND("_",D17,FIND("_",D17)+1)-FIND("_",D17)-1)),"") | N17: =IF(OR(C17="",M17=""),"",C17&" Item "&M17) | O17: 302 | P17: =G17*Q17 -> 0 | Q17: =IF(K17=TRUE(),0.1,0) -> 0
A18: TXN_7563311 | B18: CUST_23 | C18: Patisserie | D18: Item_17_PAT | E18: 29 | F18: 8 | G18: 232 | H18: Cash | I18: Online | J18: 45612 | K18: =TRUE() -> TRUE | L18: =IFERROR(INDEX(CategoryCodes!$B$2:$B$9,MATCH(C18,CategoryCodes!$A$2:$A$9,0)),"") -> H | M18: =IFERROR(VALUE(MID(D18,FIND("_",D18)+1,FIND("_",D18,FIND("_",D18)+1)-FIND("_",D18)-1)),"") -> 17 | N18: =IF(OR(C18="",M18=""),"",C18&" Item "&M18) -> Patisserie Item 17 | O18: 216 | P18: =G18*Q18 -> 23.2 | Q18: =IF(K18=TRUE(),0.1,0) -> 0.1
A19: TXN_9634894 | B19: CUST_15 | C19: Milk Products | F19: 10 | G19: 275 | H19: Digital Wallet | I19: Online | J19: 44668 | L19: =IFERROR(INDEX(CategoryCodes!$B$2:$B$9,MATCH(C19,CategoryCodes!$A$2:$A$9,0)),"") -> G | M19: =IFERROR(VALUE(MID(D19,FIND("_",D19)+1,FIND("_",D19,FIND("_",D19)+1)-FIND("_",D19)-1)),"") | N19: =IF(OR(C19="",M19=""),"",C19&" Item "&M19) | O19: 16 | P19: =G19*Q19 -> 0 | Q19: =IF(K19=TRUE(),0.1,0) -> 0
A20: TXN_4396807 | B20: CUST_17 | C20: Electric household essentials | D20: Item_13_EHE | E20: 23 | F20: 1 | G20: 23 | H20: Digital Wallet | I20: In-store | J20: 44599 | K20: =FALSE() -> FALSE | L20: =IFERROR(INDEX(CategoryCodes!$B$2:$B$9,MATCH(C20,CategoryCodes!$A$2:$A$9,0)),"") -> D | M20: =IFERROR(VALUE(MID(D20,FIND("_",D20)+1,FIND("_",D20,FIND("_",D20)+1)-FIND("_",D20)-1)),"") -> 13 | N20: =IF(OR(C20="",M20=""),"",C20&" Item "&M20) -> Electric household essentials Item 13 | O20: 15 | P20: =G20*Q20 -> 0 | Q20: =IF(K20=TRUE(),0.1,0) -> 0
A21: TXN_4206593 | B21: CUST_01 | C21: Furniture | E21: 35 | H21: Digital Wallet | I21: Online | J21: 45670 | K21: =FALSE() -> FALSE | L21: =IFERROR(INDEX(CategoryCodes!$B$2:$B$9,MATCH(C21,CategoryCodes!$A$2:$A$9,0)),"") -> F | M21: =IFERROR(VALUE(MID(D21,FIND("_",D21)+1,FIND("_",D21,FIND("_",D21)+1)-FIND("_",D21)-1)),"") | N21: =IF(OR(C21="",M21=""),"",C21&" Item "&M21) | O21: 47 | P21: =G21*Q21 -> 0 | Q21: =IF(K21=TRUE(),0.1,0) -> 0
A22: TXN_9939063 | B22: CUST_14 | C22: Beverages | D22: Item_7_BEV | E22: 14 | F22: 9 | G22: 126 | H22: Digital Wallet | I22: In-store | J22: 45305 | L22: =IFERROR(INDEX(CategoryCodes!$B$2:$B$9,MATCH(C22,CategoryCodes!$A$2:$A$9,0)),"") -> A | M22: =IFERROR(VALUE(MID(D22,FIND("_",D22)+1,FIND("_",D22,FIND("_",D22)+1)-FIND("_",D22)-1)),"") -> 7 | N22: =IF(OR(C22="",M22=""),"",C22&" Item "&M22) -> Beverages Item 7 | O22: 111 | P22: =G22*Q22 -> 0 | Q22: =IF(K22=TRUE(),0.1,0) -> 0
A23: TXN_8685338 | B23: CUST_15 | C23: Milk Products | F23: 3 | G23: 105 | H23: Credit Card | I23: In-store | J23: 45228 | L23: =IFERROR(INDEX(CategoryCodes!$B$2:$B$9,MATCH(C23,CategoryCodes!$A$2:$A$9,0)),"") -> G | M23: =IFERROR(VALUE(MID(D23,FIND("_",D23)+1,FIND("_",D23,FIND("_",D23)+1)-FIND("_",D23)-1)),"") | N23: =IF(OR(C23="",M23=""),"",C23&" Item "&M23) | O23: 119 | P23: =G23*Q23 -> 0 | Q23: =IF(K23=TRUE(),0.1,0) -> 0
A24: TXN_6547964 | B24: CUST_10 | C24: Electric household essentials | D24: Item_4_EHE | E24: 9.5 | F24: 7 | G24: 66.5 | H24: Cash | I24: In-store | J24: 44788 | L24: =IFERROR(INDEX(CategoryCodes!$B$2:$B$9,MATCH(C24,CategoryCodes!$A$2:$A$9,0)),"") -> D | M24: =IFERROR(VALUE(MID(D24,FIND("_",D24)+1,FIND("_",D24,FIND("_",D24)+1)-FIND("_",D24)-1)),"") -> 4 | N24: =IF(OR(C24="",M24=""),"",C24&" Item "&M24) -> Electric household essentials Item 4 | O24: 258 | P24: =G24*Q24 -> 0 | Q24: =IF(K24=TRUE(),0.1,0) -> 0
A25: TXN_3314099 | B25: CUST_04 | C25: Food | D25: Item_10_FOOD | E25: 18.5 | F25: 1 | G25: 18.5 | H25: Cash | I25: Online | J25: 45199 | K25: =FALSE() -> FALSE | L25: =IFERROR(INDEX(CategoryCodes!$B$2:$B$9,MATCH(C25,CategoryCodes!$A$2:$A$9,0)),"") -> E | M25: =IFERROR(VALUE(MID(D25,FIND("_",D25)+1,FIND("_",D25,FIND("_",D25)+1)-FIND("_",D25)-1)),"") -> 10 | N25: =IF(OR(C25="",M25=""),"",C25&" Item "&M25) -> Food Item 10 | O25: 308 | P25: =G25*Q25 -> 0 | Q25: =IF(K25=TRUE(),0.1,0) -> 0
A26: TXN_9980736 | B26: CUST_13 | C26: Furniture | D26: Item_14_FUR | E26: 24.5 | F26: 2 | G26: 49 | H26: Cash | I26: Online | J26: 45167 | K26: =FALSE() -> FALSE | L26: =IFERROR(INDEX(CategoryCodes!$B$2:$B$9,MATCH(C26,CategoryCodes!$A$2:$A$9,0)),"") -> F | M26: =IFERROR(VALUE(MID(D26,FIND("_",D26)+1,FIND("_",D26,FIND("_",D26)+1)-FIND("_",D26)-1)),"") -> 14 | N26: =IF(OR(C26="",M26=""),"",C26&" Item "&M26) -> Furniture Item 14 | O26: 13 | P26: =G26*Q26 -> 0 | Q26: =IF(K26=TRUE(),0.1,0) -> 0
A27: TXN_3481599 | B27: CUST_05 | C27: Furniture | E27: 39.5 | H27: Cash | I27: Online | J27: 44812 | K27: =FALSE() -> FALSE | L27: =IFERROR(INDEX(CategoryCodes!$B$2:$B$9,MATCH(C27,CategoryCodes!$A$2:$A$9,0)),"") -> F | M27: =IFERROR(VALUE(MID(D27,FIND("_",D27)+1,FIND("_",D27,FIND("_",D27)+1)-FIND("_",D27)-1)),"") | N27: =IF(OR(C27="",M27=""),"",C27&" Item "&M27) | O27: 287 | P27: =G27*Q27 -> 0 | Q27: =IF(K27=TRUE(),0.1,0) -> 0
A28: TXN_9057609 | B28: CUST_18 | C28: Butchers | D28: Item_20_BUT | E28: 33.5 | F28: 4 | G28: 134 | H28: Credit Card | I28: In-store | J28: 44636 | K28: =TRUE() -> TRUE | L28: =IFERROR(INDEX(CategoryCodes!$B$2:$B$9,MATCH(C28,CategoryCodes!$A$2:$A$9,0)),"") -> B | M28: =IFERROR(VALUE(MID(D28,FIND("_",D28)+1,FIND("_",D28,FIND("_",D28)+1)-FIND("_",D28)-1)),"") -> 20 | N28: =IF(OR(C28="",M28=""),"",C28&" Item "&M28) -> Butchers Item 20 | O28: 101 | P28: =G28*Q28 -> 13.4 | Q28: =IF(K28=TRUE(),0.1,0) -> 0.1
A29: TXN_1599706 | B29: CUST_14 | C29: Furniture | D29: Item_25_FUR | E29: 41 | F29: 10 | G29: 410 | H29: Credit Card | I29: In-store | J29: 45375 | K29: =TRUE() -> TRUE | L29: =IFERROR(INDEX(CategoryCodes!$B$2:$B$9,MATCH(C29,CategoryCodes!$A$2:$A$9,0)),"") -> F | M29: =IFERROR(VALUE(MID(D29,FIND("_",D29)+1,FIND("_",D29,FIND("_",D29)+1)-FIND("_",D29)-1)),"") -> 25 | N29: =IF(OR(C29="",M29=""),"",C29&" Item "&M29) -> Furniture Item 25 | O29: 366 | P29: =G29*Q29 -> 41 | Q29: =IF(K29=TRUE(),0.1,0) -> 0.1
A30: TXN_1598860 | B30: CUST_08 | C30: Food | D30: Item_14_FOOD | E30: 24.5 | F30: 10 | G30: 245 | H30: Cash | I30: In-store | J30: 44857 | K30: =TRUE() -> TRUE | L30: =IFERROR(INDEX(CategoryCodes!$B$2:$B$9,MATCH(C30,CategoryCodes!$A$2:$A$9,0)),"") -> E | M30: =IFERROR(VALUE(MID(D30,FIND("_",D30)+1,FIND("_",D30,FIND("_",D30)+1)-FIND("_",D30)-1)),"") -> 14 | N30: =IF(OR(C30="",M30=""),"",C30&" Item "&M30) -> Food Item 14 | O30: 332 | P30: =G30*Q30 -> 24.5 | Q30: =IF(K30=TRUE(),0.1,0) -> 0.1
A31: TXN_7138501 | B31: CUST_18 | C31: Patisserie | D31: Item_22_PAT | E31: 36.5 | F31: 5 | G31: 182.5 | H31: Credit Card | I31: In-store | J31: 44630 | K31: =FALSE() -> FALSE | L31: =IFERROR(INDEX(CategoryCodes!$B$2:$B$9,MATCH(C31,CategoryCodes!$A$2:$A$9,0)),"") -> H | M31: =IFERROR(VALUE(MID(D31,FIND("_",D31)+1,FIND("_",D31,FIND("_",D31)+1)-FIND("_",D31)-1)),"") -> 22 | N31: =IF(OR(C31="",M31=""),"",C31&" Item "&M31) -> Patisserie Item 22 | O31: 359 | P31: =G31*Q31 -> 0 | Q31: =IF(K31=TRUE(),0.1,0) -> 0
A32: TXN_5444504 | B32: CUST_05 | C32: Food | D32: Item_11_FOOD | E32: 20 | F32: 10 | G32: 200 | H32: Digital Wallet | I32: Online | J32: 44677 | K32: =FALSE() -> FALSE | L32: =IFERROR(INDEX(CategoryCodes!$B$2:$B$9,MATCH(C32,CategoryCodes!$A$2:$A$9,0)),"") -> E | M32: =IFERROR(VALUE(MID(D32,FIND("_",D32)+1,FIND("_",D32,FIND("_",D32)+1)-FIND("_",D32)-1)),"") -> 11 | N32: =IF(OR(C32="",M32=""),"",C32&" Item "&M32) -> Food Item 11 | O32: 279 | P32: =G32*Q32 -> 0 | Q32: =IF(K32=TRUE(),0.1,0) -> 0
A33: TXN_4353295 | B33: CUST_22 | C33: Patisserie | D33: Item_6_PAT | E33: 12.5 | F33: 8 | G33: 100 | H33: Credit Card | I33: Online | J33: 44656 | K33: =TRUE() -> TRUE | L33: =IFERROR(INDEX(CategoryCodes!$B$2:$B$9,MATCH(C33,CategoryCodes!$A$2:$A$9,0)),"") -> H | M33: =IFERROR(VALUE(MID(D33,FIND("_",D33)+1,FIND("_",D33,FIND("_",D33)+1)-FIND("_",D33)-1)),"") -> 6 | N33: =IF(OR(C33="",M33=""),"",C33&" Item "&M33) -> Patisserie Item 6 | O33: 214 | P33: =G33*Q33 -> 10 | Q33: =IF(K33=TRUE(),0.1,0) -> 0.1
A34: TXN_1543244 | B34: CUST_20 | C34: Food | F34: 8 | G34: 196 | H34: Credit Card | I34: Online | J34: 45590 | K34: =TRUE() -> TRUE | L34: =IFERROR(INDEX(CategoryCodes!$B$2:$B$9,MATCH(C34,CategoryCodes!$A$2:$A$9,0)),"") -> E | M34: =IFERROR(VALUE(MID(D34,FIND("_",D34)+1,FIND("_",D34,FIND("_",D34)+1)-FIND("_",D34)-1)),"") | N34: =IF(OR(C34="",M34=""),"",C34&" Item "&M34) | O34: 112 | P34: =G34*Q34 -> 19.6 | Q34: =IF(K34=TRUE(),0.1,0) -> 0.1
A35: TXN_1494700 | B35: CUST_12 | C35: Electric household essentials | D35: Item_21_EHE | E35: 35 | F35: 9 | G35: 315 | H35: Credit Card | I35: In-store | J35: 45358 | L35: =IFERROR(INDEX(CategoryCodes!$B$2:$B$9,MATCH(C35,CategoryCodes!$A$2:$A$9,0)),"") -> D | M35: =IFERROR(VALUE(MID(D35,FIND("_",D35)+1,FIND("_",D35,FIND("_",D35)+1)-FIND("_",D35)-1)),"") -> 21 | N35: =IF(OR(C35="",M35=""),"",C35&" Item "&M35) -> Electric household essentials Item 21 | O35: 229 | P35: =G35*Q35 -> 0 | Q35: =IF(K35=TRUE(),0.1,0) -> 0
A36: TXN_1621497 | B36: CUST_06 | C36: Patisserie | E36: 23 | H36: Cash | I36: In-store | J36: 44975 | L36: =IFERROR(INDEX(CategoryCodes!$B$2:$B$9,MATCH(C36,CategoryCodes!$A$2:$A$9,0)),"") -> H | M36: =IFERROR(VALUE(MID(D36,FIND("_",D36)+1,FIND("_",D36,FIND("_",D36)+1)-FIND("_",D36)-1)),"") | N36: =IF(OR(C36="",M36=""),"",C36&" Item "&M36) | O36: 301 | P36: =G36*Q36 -> 0 | Q36: =IF(K36=TRUE(),0.1,0) -> 0
A37: TXN_6398436 | B37: CUST_15 | C37: Beverages | D37: Item_25_BEV | E37: 41 | F37: 7 | G37: 287 | H37: Credit Card | I37: In-store | J37: 45446 | K37: =TRUE() -> TRUE | L37: =IFERROR(INDEX(CategoryCodes!$B$2:$B$9,MATCH(C37,CategoryCodes!$A$2:$A$9,0)),"") -> A | M37: =IFERROR(VALUE(MID(D37,FIND("_",D37)+1,FIND("_",D37,FIND("_",D37)+1)-FIND("_",D37)-1)),"") -> 25 | N37: =IF(OR(C37="",M37=""),"",C37&" Item "&M37) -> Beverages Item 25 | O37: 142 | P37: =G37*Q37 -> 28.7 | Q37: =IF(K37=TRUE(),0.1,0) -> 0.1
A38: TXN_9065245 | B38: CUST_02 | C38: Food | D38: Item_23_FOOD | E38: 38 | F38: 2 | G38: 76 | H38: Digital Wallet | I38: In-store | J38: 45361 | K38: =FALSE() -> FALSE | L38: =IFERROR(INDEX(CategoryCodes!$B$2:$B$9,MATCH(C38,CategoryCodes!$A$2:$A$9,0)),"") -> E | M38: =IFERROR(VALUE(MID(D38,FIND("_",D38)+1,FIND("_",D38,FIND("_",D38)+1)-FIND("_",D38)-1)),"") -> 23 | N38: =IF(OR(C38="",M38=""),"",C38&" Item "&M38) -> Food Item 23 | O38: 414 | P38: =G38*Q38 -> 0 | Q38: =IF(K38=TRUE(),0.1,0) -> 0
A39: TXN_6963438 | B39: CUST_11 | C39: Furniture | D39: Item_10_FUR | E39: 18.5 | F39: 5 | G39: 92.5 | H39: Credit Card | I39: Online | J39: 45405 | K39: =TRUE() -> TRUE | L39: =IFERROR(INDEX(CategoryCodes!$B$2:$B$9,MATCH(C39,CategoryCodes!$A$2:$A$9,0)),"") -> F | M39: =IFERROR(VALUE(MID(D39,FIND("_",D39)+1,FIND("_",D39,FIND("_",D39)+1)-FIND("_",D39)-1)),"") -> 10 | N39: =IF(OR(C39="",M39=""),"",C39&" Item "&M39) -> Furniture Item 10 | O39: 445 | P39: =G39*Q39 -> 9.25 | Q39: =IF(K39=TRUE(),0.1,0) -> 0.1
A40: TXN_8312797 | B40: CUST_14 | C40: Beverages | D40: Item_11_BEV | E40: 20 | F40: 5 | G40: 100 | H40: Digital Wallet | I40: Online | J40: 44715 | L40: =IFERROR(INDEX(CategoryCodes!$B$2:$B$9,MATCH(C40,CategoryCodes!$A$2:$A$9,0)),"") -> A | M40: =IFERROR(VALUE(MID(D40,FIND("_",D40)+1,FIND("_",D40,FIND("_",D40)+1)-FIND("_",D40)-1)),"") -> 11 | N40: =IF(OR(C40="",M40=""),"",C40&" Item "&M40) -> Beverages Item 11 | O40: 3 | P40: =G40*Q40 -> 0 | Q40: =IF(K40=TRUE(),0.1,0) -> 0
A41: TXN_5836005 | B41: CUST_19 | C41: Butchers | D41: Item_23_BUT | E41: 38 | F41: 5 | G41: 190 | H41: Credit Card | I41: In-store | J41: 45584 | K41: =FALSE() -> FALSE | L41: =IFERROR(INDEX(CategoryCodes!$B$2:$B$9,MATCH(C41,CategoryCodes!$A$2:$A$9,0)),"") -> B | M41: =IFERROR(VALUE(MID(D41,FIND("_",D41)+1,FIND("_",D41,FIND("_",D41)+1)-FIND("_",D41)-1)),"") -> 23 | N41: =IF(OR(C41="",M41=""),"",C41&" Item "&M41) -> Butchers Item 23 | O41: 388 | P41: =G41*Q41 -> 0 | Q41: =IF(K41=TRUE(),0.1,0) -> 0
A42: TXN_4223250 | B42: CUST_16 | C42: Beverages | D42: Item_22_BEV | E42: 36.5 | F42: 7 | G42: 255.5 | H42: Cash | I42: Online | J42: 45077 | K42: =TRUE() -> TRUE | L42: =IFERROR(INDEX(CategoryCodes!$B$2:$B$9,MATCH(C42,CategoryCodes!$A$2:$A$9,0)),"") -> A | M42: =IFERROR(VALUE(MID(D42,FIND("_",D42)+1,FIND("_",D42,FIND("_",D42)+1)-FIND("_",D42)-1)),"") -> 22 | N42: =IF(OR(C42="",M42=""),"",C42&" Item "&M42) -> Beverages Item 22 | O42: 412 | P42: =G42*Q42 -> 25.55 | Q42: =IF(K42=TRUE(),0.1,0) -> 0.1
A43: TXN_1019817 | B43: CUST_16 | C43: Electric household essentials | D43: Item_10_EHE | E43: 18.5 | F43: 5 | G43: 92.5 | H43: Cash | I43: Online | J43: 44774 | L43: =IFERROR(INDEX(CategoryCodes!$B$2:$B$9,MATCH(C43,CategoryCodes!$A$2:$A$9,0)),"") -> D | M43: =IFERROR(VALUE(MID(D43,FIND("_",D43)+1,FIND("_",D43,FIND("_",D43)+1)-FIND("_",D43)-1)),"") -> 10 | N43: =IF(OR(C43="",M43=""),"",C43&" Item "&M43) -> Electric household essentials Item 10 | O43: 81 | P43: =G43*Q43 -> 0 | Q43: =IF(K43=TRUE(),0.1,0) -> 0
A44: TXN_1110407 | B44: CUST_25 | C44: Butchers | D44: Item_24_BUT | E44: 39.5 | F44: 7 | G44: 276.5 | H44: Digital Wallet | I44: In-store | J44: 44855 | L44: =IFERROR(INDEX(CategoryCodes!$B$2:$B$9,MATCH(C44,CategoryCodes!$A$2:$A$9,0)),"") -> B | M44: =IFERROR(VALUE(MID(D44,FIND("_",D44)+1,FIND("_",D44,FIND("_",D44)+1)-FIND("_",D44)-1)),"") -> 24 | N44: =IF(OR(C44="",M44=""),"",C44&" Item "&M44) -> Butchers Item 24 | O44: 357 | P44: =G44*Q44 -> 0 | Q44: =IF(K44=TRUE(),0.1,0) -> 0
A45: TXN_6276518 | B45: CUST_24 | C45: Beverages | D45: Item_8_BEV | E45: 15.5 | F45: 3 | G45: 46.5 | H45: Cash | I45: In-store | J45: 45390 | L45: =IFERROR(INDEX(CategoryCodes!$B$2:$B$9,MATCH(C45,CategoryCodes!$A$2:$A$9,0)),"") -> A | M45: =IFERROR(VALUE(MID(D45,FIND("_",D45)+1,FIND("_",D45,FIND("_",D45)+1)-FIND("_",D45)-1)),"") -> 8 | N45: =IF(OR(C45="",M45=""),"",C45&" Item "&M45) -> Beverages Item 8 | O45: 216 | P45: =G45*Q45 -> 0 | Q45: =IF(K45=TRUE(),0.1,0) -> 0
A46: TXN_4740738 | B46: CUST_25 | C46: Food | D46: Item_3_FOOD | E46: 8 | F46: 1 | G46: 8 | H46: Digital Wallet | I46: In-store | J46: 44670 | L46: =IFERROR(INDEX(CategoryCodes!$B$2:$B$9,MATCH(C46,CategoryCodes!$A$2:$A$9,0)),"") -> E | M46: =IFERROR(VALUE(MID(D46,FIND("_",D46)+1,FIND("_",D46,FIND("_",D46)+1)-FIND("_",D46)-1)),"") -> 3 | N46: =IF(OR(C46="",M46=""),"",C46&" Item "&M46) -> Food Item 3 | O46: 174 | P46: =G46*Q46 -> 0 | Q46: =IF(K46=TRUE(),0.1,0) -> 0
A47: TXN_9587232 | B47: CUST_20 | C47: Food | D47: Item_12_FOOD | E47: 21.5 | F47: 5 | G47: 107.5 | H47: Digital Wallet | I47: Online | J47: 44985 | K47: =TRUE() -> TRUE | L47: =IFERROR(INDEX(CategoryCodes!$B$2:$B$9,MATCH(C47,CategoryCodes!$A$2:$A$9,0)),"") -> E | M47: =IFERROR(VALUE(MID(D47,FIND("_",D47)+1,FIND("_",D47,FIND("_",D47)+1)-FIND("_",D47)-1)),"") -> 12 | N47: =IF(OR(C47="",M47=""),"",C47&" Item "&M47) -> Food Item 12 | O47: 142 | P47: =G47*Q47 -> 10.75 | Q47: =IF(K47=TRUE(),0.1,0) -> 0.1
A48: TXN_6404316 | B48: CUST_04 | C48: Computers and electric accessories | D48: Item_16_CEA | E48: 27.5 | F48: 6 | G48: 165 | H48: Credit Card | I48: Online | J48: 44657 | K48: =FALSE() -> FALSE | L48: =IFERROR(INDEX(CategoryCodes!$B$2:$B$9,MATCH(C48,CategoryCodes!$A$2:$A$9,0)),"") -> C | M48: =IFERROR(VALUE(MID(D48,FIND("_",D48)+1,FIND("_",D48,FIND("_",D48)+1)-FIND("_",D48)-1)),"") -> 16 | N48: =IF(OR(C48="",M48=""),"",C48&" Item "&M48) -> Computers and electric accessories Item 16 | O48: 79 | P48: =G48*Q48 -> 0 | Q48: =IF(K48=TRUE(),0.1,0) -> 0
A49: TXN_9331642 | B49: CUST_12 | C49: Patisserie | D49: Item_11_PAT | E49: 20 | F49: 4 | G49: 80 | H49: Credit Card | I49: Online | J49: 44748 | K49: =TRUE() -> TRUE | L49: =IFERROR(INDEX(CategoryCodes!$B$2:$B$9,MATCH(C49,CategoryCodes!$A$2:$A$9,0)),"") -> H | M49: =IFERROR(VALUE(MID(D49,FIND("_",D49)+1,FIND("_",D49,FIND("_",D49)+1)-FIND("_",D49)-1)),"") -> 11 | N49: =IF(OR(C49="",M49=""),"",C49&" Item "&M49) -> Patisserie Item 11 | O49: 110 | P49: =G49*Q49 -> 8 | Q49: =IF(K49=TRUE(),0.1,0) -> 0.1
A50: TXN_9729422 | B50: CUST_13 | C50: Butchers | D50: Item_16_BUT | E50: 27.5 | F50: 6 | G50: 165 | H50: Credit Card | I50: Online | J50: 45657 | K50: =TRUE() -> TRUE | L50: =IFERROR(INDEX(CategoryCodes!$B$2:$B$9,MATCH(C50,CategoryCodes!$A$2:$A$9,0)),"") -> B | M50: =IFERROR(VALUE(MID(D50,FIND("_",D50)+1,FIND("_",D50,FIND("_",D50)+1)-FIND("_",D50)-1)),"") -> 16 | N50: =IF(OR(C50="",M50=""),"",C50&" Item "&M50) -> Butchers Item 16 | O50: 490 | P50: =G50*Q50 -> 16.5 | Q50: =IF(K50=TRUE(),0.1,0) -> 0.1
A51: TXN_8425168 | B51: CUST_25 | C51: Milk Products | D51: Item_16_MILK | E51: 27.5 | F51: 7 | G51: 192.5 | H51: Cash | I51: In-store | J51: 44632 | L51: =IFERROR(INDEX(CategoryCodes!$B$2:$B$9,MATCH(C51,CategoryCodes!$A$2:$A$9,0)),"") -> G | M51: =IFERROR(VALUE(MID(D51,FIND("_",D51)+1,FIND("_",D51,FIND("_",D51)+1)-FIND("_",D51)-1)),"") -> 16 | N51: =IF(OR(C51="",M51=""),"",C51&" Item "&M51) -> Milk Products Item 16 | O51: 390 | P51: =G51*Q51 -> 0 | Q51: =IF(K51=TRUE(),0.1,0) -> 0
A52: TXN_5379241 | B52: CUST_05 | C52: Butchers | D52: Item_20_BUT | E52: 33.5 | F52: 10 | G52: 335 | H52: Credit Card | I52: In-store | J52: 45028 | K52: =FALSE() -> FALSE | L52: =IFERROR(INDEX(CategoryCodes!$B$2:$B$9,MATCH(C52,CategoryCodes!$A$2:$A$9,0)),"") -> B | M52: =IFERROR(VALUE(MID(D52,FIND("_",D52)+1,FIND("_",D52,FIND("_",D52)+1)-FIND("_",D52)-1)),"") -> 20 | N52: =IF(OR(C52="",M52=""),"",C52&" Item "&M52) -> Butchers Item 20 | O52: 172 | P52: =G52*Q52 -> 0 | Q52: =IF(K52=TRUE(),0.1,0) -> 0
A53: TXN_8413369 | B53: CUST_23 | C53: Computers and electric accessories | D53: Item_5_CEA | E53: 11 | F53: 6 | G53: 66 | H53: Credit Card | I53: Online | J53: 45360 | K53: =TRUE() -> TRUE | L53: =IFERROR(INDEX(CategoryCodes!$B$2:$B$9,MATCH(C53,CategoryCodes!$A$2:$A$9,0)),"") -> C | M53: =IFERROR(VALUE(MID(D53,FIND("_",D53)+1,FIND("_",D53,FIND("_",D53)+1)-FIND("_",D53)-1)),"") -> 5 | N53: =IF(OR(C53="",M53=""),"",C53&" Item "&M53) -> Computers and electric accessories Item 5 | O53: 52 | P53: =G53*Q53 -> 6.6 | Q53: =IF(K53=TRUE(),0.1,0) -> 0.1
A54: TXN_4836321 | B54: CUST_21 | C54: Food | D54: Item_12_FOOD | E54: 21.5 | F54: 10 | G54: 215 | H54: Digital Wallet | I54: In-store | J54: 44940 | K54: =FALSE() -> FALSE | L54: =IFERROR(INDEX(CategoryCodes!$B$2:$B$9,MATCH(C54,CategoryCodes!$A$2:$A$9,0)),"") -> E | M54: =IFERROR(VALUE(MID(D54,FIND("_",D54)+1,FIND("_",D54,FIND("_",D54)+1)-FIND("_",D54)-1)),"") -> 12 | N54: =IF(OR(C54="",M54=""),"",C54&" Item "&M54) -> Food Item 12 | O54: 47 | P54: =G54*Q54 -> 0 | Q54: =IF(K54=TRUE(),0.1,0) -> 0
A55: TXN_9451794 | B55: CUST_24 | C55: Milk Products | D55: Item_19_MILK | E55: 32 | F55: 3 | G55: 96 | H55: Credit Card | I55: Online | J55: 45319 | L55: =IFERROR(INDEX(CategoryCodes!$B$2:$B$9,MATCH(C55,CategoryCodes!$A$2:$A$9,0)),"") -> G | M55: =IFERROR(VALUE(MID(D55,FIND("_",D55)+1,FIND("_",D55,FIND("_",D55)+1)-FIND("_",D55)-1)),"") -> 19 | N55: =IF(OR(C55="",M55=""),"",C55&" Item "&M55) -> Milk Products Item 19 | O55: 194 | P55: =G55*Q55 -> 0 | Q55: =IF(K55=TRUE(),0.1,0) -> 0
A56: TXN_8218431 | B56: CUST_01 | C56: Furniture | D56: Item_23_FUR | E56: 38 | F56: 5 | G56: 190 | H56: Digital Wallet | I56: Online | J56: 45045 | K56: =FALSE() -> FALSE | L56: =IFERROR(INDEX(CategoryCodes!$B$2:$B$9,MATCH(C56,CategoryCodes!$A$2:$A$9,0)),"") -> F | M56: =IFERROR(VALUE(MID(D56,FIND("_",D56)+1,FIND("_",D56,FIND("_",D56)+1)-FIND("_",D56)-1)),"") -> 23 | N56: =IF(OR(C56="",M56=""),"",C56&" Item "&M56) -> Furniture Item 23 | O56: 49 | P56: =G56*Q56 -> 0 | Q56: =IF(K56=TRUE(),0.1,0) -> 0
A57: TXN_2383377 | B57: CUST_15 | C57: Furniture | D57: Item_7_FUR | E57: 14 | F57: 3 | G57: 42 | H57: Digital Wallet | I57: In-store | J57: 45018 | L57: =IFERROR(INDEX(CategoryCodes!$B$2:$B$9,MATCH(C57,CategoryCodes!$A$2:$A$9,0)),"") -> F | M57: =IFERROR(VALUE(MID(D57,FIND("_",D57)+1,FIND("_",D57,FIND("_",D57)+1)-FIND("_",D57)-1)),"") -> 7 | N57: =IF(OR(C57="",M57=""),"",C57&" Item "&M57) -> Furniture Item 7 | O57: 183 | P57: =G57*Q57 -> 0 | Q57: =IF(K57=TRUE(),0.1,0) -> 0
A58: TXN_7909783 | B58: CUST_12 | C58: Computers and electric accessories | D58: Item_5_CEA | E58: 11 | F58: 1 | G58: 11 | H58: Credit Card | I58: Online | J58: 45277 | K58: =TRUE() -> TRUE | L58: =IFERROR(INDEX(CategoryCodes!$B$2:$B$9,MATCH(C58,CategoryCodes!$A$2:$A$9,0)),"") -> C | M58: =IFERROR(VALUE(MID(D58,FIND("_",D58)+1,FIND("_",D58,FIND("_",D58)+1)-FIND("_",D58)-1)),"") -> 5 | N58: =IF(OR(C58="",M58=""),"",C58&" Item "&M58) -> Computers and electric accessories Item 5 | O58: 433 | P58: =G58*Q58 -> 1.1 | Q58: =IF(K58=TRUE(),0.1,0) -> 0.1
A59: TXN_5046007 | B59: CUST_07 | C59: Computers and electric accessories | D59: Item_15_CEA | E59: 26 | F59: 9 | G59: 234 | H59: Cash | I59: Online | J59: 45495 | K59: =TRUE() -> TRUE | L59: =IFERROR(INDEX(CategoryCodes!$B$2:$B$9,MATCH(C59,CategoryCodes!$A$2:$A$9,0)),"") -> C | M59: =IFERROR(VALUE(MID(D59,FIND("_",D59)+1,FIND("_",D59,FIND("_",D59)+1)-FIND("_",D59)-1)),"") -> 15 | N59: =IF(OR(C59="",M59=""),"",C59&" Item "&M59) -> Computers and electric accessories Item 15 | O59: 176 | P59: =G59*Q59 -> 23.4 | Q59: =IF(K59=TRUE(),0.1,0) -> 0.1
A60: TXN_6966182 | B60: CUST_02 | C60: Furniture | D60: Item_16_FUR | E60: 27.5 | F60: 9 | G60: 247.5 | H60: Cash | I60: Online | J60: 45541 | L60: =IFERROR(INDEX(CategoryCodes!$B$2:$B$9,MATCH(C60,CategoryCodes!$A$2:$A$9,0)),"") -> F | M60: =IFERROR(VALUE(MID(D60,FIND("_",D60)+1,FIND("_",D60,FIND("_",D60)+1)-FIND("_",D60)-1)),"") -> 16 | N60: =IF(OR(C60="",M60=""),"",C60&" Item "&M60) -> Furniture Item 16 | O60: 309 | P60: =G60*Q60 -> 0 | Q60: =IF(K60=TRUE(),0.1,0) -> 0
A61: TXN_3424571 | B61: CUST_09 | C61: Milk Products | D61: Item_6_MILK | E61: 12.5 | F61: 7 | G61: 87.5 | H61: Credit Card | I61: Online | J61: 44939 | K61: =FALSE() -> FALSE | L61: =IFERROR(INDEX(CategoryCodes!$B$2:$B$9,MATCH(C61,CategoryCodes!$A$2:$A$9,0)),"") -> G | M61: =IFERROR(VALUE(MID(D61,FIND("_",D61)+1,FIND("_",D61,FIND("_",D61)+1)-FIND("_",D61)-1)),"") -> 6 | N61: =IF(OR(C61="",M61=""),"",C61&" Item "&M61) -> Milk Products Item 6 | O61: 135 | P61: =G61*Q61 -> 0 | Q61: =IF(K61=TRUE(),0.1,0) -> 0
A62: TXN_6820452 | B62: CUST_10 | C62: Computers and electric accessories | D62: Item_24_CEA | E62: 39.5 | F62: 8 | G62: 316 | H62: Credit Card | I62: In-store | J62: 45034 | K62: =FALSE() -> FALSE | L62: =IFERROR(INDEX(CategoryCodes!$B$2:$B$9,MATCH(C62,CategoryCodes!$A$2:$A$9,0)),"") -> C | M62: =IFERROR(VALUE(MID(D62,FIND("_",D62)+1,FIND("_",D62,FIND("_",D62)+1)-FIND("_",D62)-1)),"") -> 24 | N62: =IF(OR(C62="",M62=""),"",C62&" Item "&M62) -> Computers and electric accessories Item 24 | O62: 413 | P62: =G62*Q62 -> 0 | Q62: =IF(K62=TRUE(),0.1,0) -> 0
A63: TXN_1998771 | B63: CUST_25 | C63: Milk Products | D63: Item_16_MILK | E63: 27.5 | F63: 3 | G63: 82.5 | H63: Digital Wallet | I63: Online | J63: 45603 | K63: =TRUE() -> TRUE | L63: =IFERROR(INDEX(CategoryCodes!$B$2:$B$9,MATCH(C63,CategoryCodes!$A$2:$A$9,0)),"") -> G | M63: =IFERROR(VALUE(MID(D63,FIND("_",D63)+1,FIND("_",D63,FIND("_",D63)+1)-FIND("_",D63)-1)),"") -> 16 | N63: =IF(OR(C63="",M63=""),"",C63&" Item "&M63) -> Milk Products Item 16 | O63: 22 | P63: =G63*Q63 -> 8.25 | Q63: =IF(K63=TRUE(),0.1,0) -> 0.1
A64: TXN_1132097 | B64: CUST_24 | C64: Patisserie | D64: Item_11_PAT | E64: 20 | F64: 9 | G64: 180 | H64: Credit Card | I64: In-store | J64: 45064 | K64: =TRUE() -> TRUE | L64: =IFERROR(INDEX(CategoryCodes!$B$2:$B$9,MATCH(C64,CategoryCodes!$A$2:$A$9,0)),"") -> H | M64: =IFERROR(VALUE(MID(D64,FIND("_",D64)+1,FIND("_",D64,FIND("_",D64)+1)-FIND("_",D64)-1)),"") -> 11 | N64: =IF(OR(C64="",M64=""),"",C64&" Item "&M64) -> Patisserie Item 11 | O64: 373 | P64: =G64*Q64 -> 18 | Q64: =IF(K64=TRUE(),0.1,0) -> 0.1
A65: TXN_5418871 | B65: CUST_04 | C65: Computers and electric accessories | D65: Item_22_CEA | E65: 36.5 | F65: 7 | G65: 255.5 | H65: Cash | I65: In-store | J65: 44636 | K65: =FALSE() -> FALSE | L65: =IFERROR(INDEX(CategoryCodes!$B$2:$B$9,MATCH(C65,CategoryCodes!$A$2:$A$9,0)),"") -> C | M65: =IFERROR(VALUE(MID(D65,FIND("_",D65)+1,FIND("_",D65,FIND("_",D65)+1)-FIND("_",D65)-1)),"") -> 22 | N65: =IF(OR(C65="",M65=""),"",C65&" Item "&M65) -> Computers and electric accessories Item 22 | O65: 235 | P65: =G65*Q65 -> 0 | Q65: =IF(K65=TRUE(),0.1,0) -> 0
A66: TXN_6952276 | B66: CUST_01 | C66: Food | D66: Item_22_FOOD | E66: 36.5 | F66: 10 | G66: 365 | H66: Credit Card | I66: Online | J66: 45506 | K66: =TRUE() -> TRUE | L66: =IFERROR(INDEX(CategoryCodes!$B$2:$B$9,MATCH(C66,CategoryCodes!$A$2:$A$9,0)),"") -> E | M66: =IFERROR(VALUE(MID(D66,FIND("_",D66)+1,FIND("_",D66,FIND("_",D66)+1)-FIND("_",D66)-1)),"") -> 22 | N66: =IF(OR(C66="",M66=""),"",C66&" Item "&M66) -> Food Item 22 | O66: 274 | P66: =G66*Q66 -> 36.5 | Q66: =IF(K66=TRUE(),0.1,0) -> 0.1
A67: TXN_6340470 | B67: CUST_17 | C67: Butchers | D67: Item_2_BUT | E67: 6.5 | F67: 6 | G67: 39 | H67: Credit Card | I67: In-store | J67: 44846 | L67: =IFERROR(INDEX(CategoryCodes!$B$2:$B$9,MATCH(C67,CategoryCodes!$A$2:$A$9,0)),"") -> B | M67: =IFERROR(VALUE(MID(D67,FIND("_",D67)+1,FIND("_",D67,FIND("_",D67)+1)-FIND("_",D67)-1)),"") -> 2 | N67: =IF(OR(C67="",M67=""),"",C67&" Item "&M67) -> Butchers Item 2 | O67: 63 | P67: =G67*Q67 -> 0 | Q67: =IF(K67=TRUE(),0.1,0) -> 0
A68: TXN_5885894 | B68: CUST_01 | C68: Patisserie | D68: Item_14_PAT | E68: 24.5 | F68: 10 | G68: 245 | H68: Credit Card | I68: In-store | J68: 44601 | K68: =FALSE() -> FALSE | L68: =IFERROR(INDEX(CategoryCodes!$B$2:$B$9,MATCH(C68,CategoryCodes!$A$2:$A$9,0)),"") -> H | M68: =IFERROR(VALUE(MID(D68,FIND("_",D68)+1,FIND("_",D68,FIND("_",D68)+1)-FIND("_",D68)-1)),"") -> 14 | N68: =IF(OR(C68="",M68=""),"",C68&" Item "&M68) -> Patisserie Item 14 | O68: 498 | P68: =G68*Q68 -> 0 | Q68: =IF(K68=TRUE(),0.1,0) -> 0
A69: TXN_3671271 | B69: CUST_18 | C69: Patisserie | D69: Item_12_PAT | E69: 21.5 | F69: 8 | G69: 172 | H69: Cash | I69: In-store | J69: 45257 | K69: =FALSE() -> FALSE | L69: =IFERROR(INDEX(CategoryCodes!$B$2:$B$9,MATCH(C69,CategoryCodes!$A$2:$A$9,0)),"") -> H | M69: =IFERROR(VALUE(MID(D69,FIND("_",D69)+1,FIND("_",D69,FIND("_",D69)+1)-FIND("_",D69)-1)),"") -> 12 | N69: =IF(OR(C69="",M69=""),"",C69&" Item "&M69) -> Patisserie Item 12 | O69: 472 | P69: =G69*Q69 -> 0 | Q69: =IF(K69=TRUE(),0.1,0) -> 0
A70: TXN_2719047 | B70: CUST_03 | C70: Butchers | D70: Item_20_BUT | E70: 33.5 | F70: 4 | G70: 134 | H70: Credit Card | I70: Online | J70: 45251 | L70: =IFERROR(INDEX(CategoryCodes!$B$2:$B$9,MATCH(C70,CategoryCodes!$A$2:$A$9,0)),"") -> B | M70: =IFERROR(VALUE(MID(D70,FIND("_",D70)+1,FIND("_",D70,FIND("_",D70)+1)-FIND("_",D70)-1)),"") -> 20 | N70: =IF(OR(C70="",M70=""),"",C70&" Item "&M70) -> Butchers Item 20 | O70: 193 | P70: =G70*Q70 -> 0 | Q70: =IF(K70=TRUE(),0.1,0) -> 0
A71: TXN_9908330 | B71: CUST_19 | C71: Food | D71: Item_18_FOOD | E71: 30.5 | F71: 4 | G71: 122 | H71: Credit Card | I71: Online | J71: 44833 | K71: =TRUE() -> TRUE | L71: =IFERROR(INDEX(CategoryCodes!$B$2:$B$9,MATCH(C71,CategoryCodes!$A$2:$A$9,0)),"") -> E | M71: =IFERROR(VALUE(MID(D71,FIND("_",D71)+1,FIND("_",D71,FIND("_",D71)+1)-FIND("_",D71)-1)),"") -> 18 | N71: =IF(OR(C71="",M71=""),"",C71&" Item "&M71) -> Food Item 18 | O71: 40 | P71: =G71*Q71 -> 12.2 | Q71: =IF(K71=TRUE(),0.1,0) -> 0.1
A72: TXN_2016332 | B72: CUST_17 | C72: Patisserie | D72: Item_1_PAT | E72: 5 | F72: 6 | G72: 30 | H72: Digital Wallet | I72: Online | J72: 44912 | K72: =TRUE() -> TRUE | L72: =IFERROR(INDEX(CategoryCodes!$B$2:$B$9,MATCH(C72,CategoryCodes!$A$2:$A$9,0)),"") -> H | M72: =IFERROR(VALUE(MID(D72,FIND("_",D72)+1,FIND("_",D72,FIND("_",D72)+1)-FIND("_",D72)-1)),"") -> 1 | N72: =IF(OR(C72="",M72=""),"",C72&" Item "&M72) -> Patisserie Item 1 | O72: 282 | P72: =G72*Q72 -> 3 | Q72: =IF(K72=TRUE(),0.1,0) -> 0.1
A73: TXN_7363165 | B73: CUST_25 | C73: Beverages | D73: Item_4_BEV | E73: 9.5 | F73: 7 | G73: 66.5 | H73: Digital Wallet | I73: In-store | J73: 45010 | L73: =IFERROR(INDEX(CategoryCodes!$B$2:$B$9,MATCH(C73,CategoryCodes!$A$2:$A$9,0)),"") -> A | M73: =IFERROR(VALUE(MID(D73,FIND("_",D73)+1,FIND("_",D73,FIND("_",D73)+1)-FIND("_",D73)-1)),"") -> 4 | N73: =IF(OR(C73="",M73=""),"",C73&" Item "&M73) -> Beverages Item 4 | O73: 150 | P73: =G73*Q73 -> 0 | Q73: =IF(K73=TRUE(),0.1,0) -> 0
A74: TXN_1260450 | B74: CUST_25 | C74: Furniture | D74: Item_22_FUR | E74: 36.5 | F74: 10 | G74: 365 | H74: Digital Wallet | I74: In-store | J74: 45284 | K74: =TRUE() -> TRUE | L74: =IFERROR(INDEX(CategoryCodes!$B$2:$B$9,MATCH(C74,CategoryCodes!$A$2:$A$9,0)),"") -> F | M74: =IFERROR(VALUE(MID(D74,FIND("_",D74)+1,FIND("_",D74,FIND("_",D74)+1)-FIND("_",D74)-1)),"") -> 22 | N74: =IF(OR(C74="",M74=""),"",C74&" Item "&M74) -> Furniture Item 22 | O74: 424 | P74: =G74*Q74 -> 36.5 | Q74: =IF(K74=TRUE(),0.1,0) -> 0.1
A75: TXN_6315447 | B75: CUST_21 | C75: Patisserie | D75: Item_7_PAT | E75: 14 | F75: 9 | G75: 126 | H75: Digital Wallet | I75: In-store | J75: 45669 | K75: =FALSE() -> FALSE | L75: =IFERROR(INDEX(CategoryCodes!$B$2:$B$9,MATCH(C75,CategoryCodes!$A$2:$A$9,0)),"") -> H | M75: =IFERROR(VALUE(MID(D75,FIND("_",D75)+1,FIND("_",D75,FIND("_",D75)+1)-FIND("_",D75)-1)),"") -> 7 | N75: =IF(OR(C75="",M75=""),"",C75&" Item "&M75) -> Patisserie Item 7 | O75: 321 | P75: =G75*Q75 -> 0 | Q75: =IF(K75=TRUE(),0.1,0) -> 0
A76: TXN_5973228 | B76: CUST_12 | C76: Beverages | D76: Item_7_BEV | E76: 14 | F76: 6 | G76: 84 | H76: Digital Wallet | I76: Online | J76: 45285 | K76: =TRUE() -> TRUE | L76: =IFERROR(INDEX(CategoryCodes!$B$2:$B$9,MATCH(C76,CategoryCodes!$A$2:$A$9,0)),"") -> A | M76: =IFERROR(VALUE(MID(D76,FIND("_",D76)+1,FIND("_",D76,FIND("_",D76)+1)-FIND("_",D76)-1)),"") -> 7 | N76: =IF(OR(C76="",M76=""),"",C76&" Item "&M76) -> Beverages Item 7 | O76: 316 | P76: =G76*Q76 -> 8.4 | Q76: =IF(K76=TRUE(),0.1,0) -> 0.1
A77: TXN_2780662 | B77: CUST_02 | C77: Milk Products | D77: Item_19_MILK | E77: 32 | F77: 10 | G77: 320 | H77: Digital Wallet | I77: In-store | J77: 44945 | L77: =IFERROR(INDEX(CategoryCodes!$B$2:$B$9,MATCH(C77,CategoryCodes!$A$2:$A$9,0)),"") -> G | M77: =IFERROR(VALUE(MID(D77,FIND("_",D77)+1,FIND("_",D77,FIND("_",D77)+1)-FIND("_",D77)-1)),"") -> 19 | N77: =IF(OR(C77="",M77=""),"",C77&" Item "&M77) -> Milk Products Item 19 | O77: 453 | P77: =G77*Q77 -> 0 | Q77: =IF(K77=TRUE(),0.1,0) -> 0
A78: TXN_1142481 | B78: CUST_02 | C78: Beverages | D78: Item_22_BEV | E78: 36.5 | F78: 6 | G78: 219 | H78: Cash | I78: In-store | J78: 44964 | K78: =TRUE() -> TRUE | L78: =IFERROR(INDEX(CategoryCodes!$B$2:$B$9,MATCH(C78,CategoryCodes!$A$2:$A$9,0)),"") -> A | M78: =IFERROR(VALUE(MID(D78,FIND("_",D78)+1,FIND("_",D78,FIND("_",D78)+1)-FIND("_",D78)-1)),"") -> 22 | N78: =IF(OR(C78="",M78=""),"",C78&" Item "&M78) -> Beverages Item 22 | O78: 441 | P78: =G78*Q78 -> 21.9 | Q78: =IF(K78=TRUE(),0.1,0) -> 0.1
A79: TXN_3933685 | B79: CUST_09 | C79: Computers and electric accessories | D79: Item_20_CEA | E79: 33.5 | F79: 10 | G79: 335 | H79: Credit Card | I79: Online | J79: 44666 | L79: =IFERROR(INDEX(CategoryCodes!$B$2:$B$9,MATCH(C79,CategoryCodes!$A$2:$A$9,0)),"") -> C | M79: =IFERROR(VALUE(MID(D79,FIND("_",D79)+1,FIND("_",D79,FIND("_",D79)+1)-FIND("_",D79)-1)),"") -> 20 | N79: =IF(OR(C79="",M79=""),"",C79&" Item "&M79) -> Computers and electric accessories Item 20 | O79: 185 | P79: =G79*Q79 -> 0 | Q79: =IF(K79=TRUE(),0.1,0) -> 0
A80: TXN_8955685 | B80: CUST_24 | C80: Food | D80: Item_20_FOOD | E80: 33.5 | F80: 2 | G80: 67 | H80: Digital Wallet | I80: Online | J80: 45040 | L80: =IFERROR(INDEX(CategoryCodes!$B$2:$B$9,MATCH(C80,CategoryCodes!$A$2:$A$9,0)),"") -> E | M80: =IFERROR(VALUE(MID(D80,FIND("_",D80)+1,FIND("_",D80,FIND("_",D80)+1)-FIND("_",D80)-1)),"") -> 20 | N80: =IF(OR(C80="",M80=""),"",C80&" Item "&M80) -> Food Item 20 | O80: 295 | P80: =G80*Q80 -> 0 | Q80: =IF(K80=TRUE(),0.1,0) -> 0
A81: TXN_1061030 | B81: CUST_20 | C81: Computers and electric accessories | D81: Item_22_CEA | E81: 36.5 | F81: 4 | G81: 146 | H81: Digital Wallet | I81: Online | J81: 45487 | K81: =TRUE() -> TRUE | L81: =IFERROR(INDEX(CategoryCodes!$B$2:$B$9,MATCH(C81,CategoryCodes!$A$2:$A$9,0)),"") -> C | M81: =IFERROR(VALUE(MID(D81,FIND("_",D81)+1,FIND("_",D81,FIND("_",D81)+1)-FIND("_",D81)-1)),"") -> 22 | N81: =IF(OR(C81="",M81=""),"",C81&" Item "&M81) -> Computers and electric accessories Item 22 | O81: 98 | P81: =G81*Q81 -> 14.6 | Q81: =IF(K81=TRUE(),0.1,0) -> 0.1
A82: TXN_7821493 | B82: CUST_07 | C82: Patisserie | D82: Item_17_PAT | E82: 29 | F82: 10 | G82: 290 | H82: Credit Card | I82: In-store | J82: 45643 | L82: =IFERROR(INDEX(CategoryCodes!$B$2:$B$9,MATCH(C82,CategoryCodes!$A$2:$A$9,0)),"") -> H | M82: =IFERROR(VALUE(MID(D82,FIND("_",D82)+1,FIND("_",D82,FIND("_",D82)+1)-FIND("_",D82)-1)),"") -> 17 | N82: =IF(OR(C82="",M82=""),"",C82&" Item "&M82) -> Patisserie Item 17 | O82: 360 | P82: =G82*Q82 -> 0 | Q82: =IF(K82=TRUE(),0.1,0) -> 0
A83: TXN_8114453 | B83: CUST_10 | C83: Electric household essentials | D83: Item_21_EHE | E83: 35 | F83: 2 | G83: 70 | H83: Digital Wallet | I83: In-store | J83: 45055 | K83: =FALSE() -> FALSE | L83: =IFERROR(INDEX(CategoryCodes!$B$2:$B$9,MATCH(C83,CategoryCodes!$A$2:$A$9,0)),"") -> D | M83: =IFERROR(VALUE(MID(D83,FIND("_",D83)+1,FIND("_",D83,FIND("_",D83)+1)-FIND("_",D83)-1)),"") -> 21 | N83: =IF(OR(C83="",M83=""),"",C83&" Item "&M83) -> Electric household essentials Item 21 | O83: 35 | P83: =G83*Q83 -> 0 | Q83: =IF(K83=TRUE(),0.1,0) -> 0
A84: TXN_8024803 | B84: CUST_09 | C84: Furniture | D84: Item_11_FUR | E84: 20 | F84: 8 | G84: 160 | H84: Digital Wallet | I84: In-store | J84: 45526 | K84: =FALSE() -> FALSE | L84: =IFERROR(INDEX(CategoryCodes!$B$2:$B$9,MATCH(C84,CategoryCodes!$A$2:$A$9,0)),"") -> F | M84: =IFERROR(VALUE(MID(D84,FIND("_",D84)+1,FIND("_",D84,FIND("_",D84)+1)-FIND("_",D84)-1)),"") -> 11 | N84: =IF(OR(C84="",M84=""),"",C84&" Item "&M84) -> Furniture Item 11 | O84: 23 | P84: =G84*Q84 -> 0 | Q84: =IF(K84=TRUE(),0.1,0) -> 0
A85: TXN_4532214 | B85: CUST_25 | C85: Patisserie | E85: 15.5 | H85: Credit Card | I85: In-store | J85: 45376 | K85: =FALSE() -> FALSE | L85: =IFERROR(INDEX(CategoryCodes!$B$2:$B$9,MATCH(C85,CategoryCodes!$A$2:$A$9,0)),"") -> H | M85: =IFERROR(VALUE(MID(D85,FIND("_",D85)+1,FIND("_",D85,FIND("_",D85)+1)-FIND("_",D85)-1)),"") | N85: =IF(OR(C85="",M85=""),"",C85&" Item "&M85) | O85: 338 | P85: =G85*Q85 -> 0 | Q85: =IF(K85=TRUE(),0.1,0) -> 0
A86: TXN_5062634 | B86: CUST_04 | C86: Patisserie | D86: Item_25_PAT | E86: 41 | F86: 2 | G86: 82 | H86: Credit Card | I86: Online | J86: 45113 | K86: =TRUE() -> TRUE | L86: =IFERROR(INDEX(CategoryCodes!$B$2:$B$9,MATCH(C86,CategoryCodes!$A$2:$A$9,0)),"") -> H | M86: =IFERROR(VALUE(MID(D86,FIND("_",D86)+1,FIND("_",D86,FIND("_",D86)+1)-FIND("_",D86)-1)),"") -> 25 | N86: =IF(OR(C86="",M86=""),"",C86&" Item "&M86) -> Patisserie Item 25 | O86: 116 | P86: =G86*Q86 -> 8.2 | Q86: =IF(K86=TRUE(),0.1,0) -> 0.1
A87: TXN_8244728 | B87: CUST_08 | C87: Food | D87: Item_7_FOOD | E87: 14 | F87: 1 | G87: 14 | H87: Credit Card | I87: In-store | J87: 45409 | L87: =IFERROR(INDEX(CategoryCodes!$B$2:$B$9,MATCH(C87,CategoryCodes!$A$2:$A$9,0)),"") -> E | M87: =IFERROR(VALUE(MID(D87,FIND("_",D87)+1,FIND("_",D87,FIND("_",D87)+1)-FIND("_",D87)-1)),"") -> 7 | N87: =IF(OR(C87="",M87=""),"",C87&" Item "&M87) -> Food Item 7 | O87: 395 | P87: =G87*Q87 -> 0 | Q87: =IF(K87=TRUE(),0.1,0) -> 0
A88: TXN_3858145 | B88: CUST_17 | C88: Furniture | D88: Item_21_FUR | E88: 35 | F88: 3 | G88: 105 | H88: Digital Wallet | I88: Online | J88: 45017 | L88: =IFERROR(INDEX(CategoryCodes!$B$2:$B$9,MATCH(C88,CategoryCodes!$A$2:$A$9,0)),"") -> F | M88: =IFERROR(VALUE(MID(D88,FIND("_",D88)+1,FIND("_",D88,FIND("_",D88)+1)-FIND("_",D88)-1)),"") -> 21 | N88: =IF(OR(C88="",M88=""),"",C88&" Item "&M88) -> Furniture Item 21 | O88: 148 | P88: =G88*Q88 -> 0 | Q88: =IF(K88=TRUE(),0.1,0) -> 0
A89: TXN_2646301 | B89: CUST_18 | C89: Furniture | D89: Item_24_FUR | E89: 39.5 | F89: 9 | G89: 355.5 | H89: Credit Card | I89: In-store | J89: 44902 | K89: =FALSE() -> FALSE | L89: =IFERROR(INDEX(CategoryCodes!$B$2:$B$9,MATCH(C89,CategoryCodes!$A$2:$A$9,0)),"") -> F | M89: =IFERROR(VALUE(MID(D89,FIND("_",D89)+1,FIND("_",D89,FIND("_",D89)+1)-FIND("_",D89)-1)),"") -> 24 | N89: =IF(OR(C89="",M89=""),"",C89&" Item "&M89) -> Furniture Item 24 | O89: 40 | P89: =G89*Q89 -> 0 | Q89: =IF(K89=TRUE(),0.1,0) -> 0
A90: TXN_2414530 | B90: CUST_24 | C90: Milk Products | D90: Item_8_MILK | E90: 15.5 | F90: 8 | G90: 124 | H90: Cash | I90: Online | J90: 45463 | L90: =IFERROR(INDEX(CategoryCodes!$B$2:$B$9,MATCH(C90,CategoryCodes!$A$2:$A$9,0)),"") -> G | M90: =IFERROR(VALUE(MID(D90,FIND("_",D90)+1,FIND("_",D90,FIND("_",D90)+1)-FIND("_",D90)-1)),"") -> 8 | N90: =IF(OR(C90="",M90=""),"",C90&" Item "&M90) -> Milk Products Item 8 | O90: 437 | P90: =G90*Q90 -> 0 | Q90: =IF(K90=TRUE(),0.1,0) -> 0
A91: TXN_8322008 | B91: CUST_22 | C91: Food | D91: Item_4_FOOD | E91: 9.5 | F91: 3 | G91: 28.5 | H91: Cash | I91: In-store | J91: 45524 | K91: =FALSE() -> FALSE | L91: =IFERROR(INDEX(CategoryCodes!$B$2:$B$9,MATCH(C91,CategoryCodes!$A$2:$A$9,0)),"") -> E | M91: =IFERROR(VALUE(MID(D91,FIND("_",D91)+1,FIND("_",D91,FIND("_",D91)+1)-FIND("_",D91)-1)),"") -> 4 | N91: =IF(OR(C91="",M91=""),"",C91&" Item "&M91) -> Food Item 4 | O91: 119 | P91: =G91*Q91 -> 0 | Q91: =IF(K91=TRUE(),0.1,0) -> 0
A92: TXN_3035546 | B92: CUST_19 | C92: Beverages | D92: Item_14_BEV | E92: 24.5 | F92: 2 | G92: 49 | H92: Credit Card | I92: In-store | J92: 45119 | K92: =TRUE() -> TRUE | L92: =IFERROR(INDEX(CategoryCodes!$B$2:$B$9,MATCH(C92,CategoryCodes!$A$2:$A$9,0)),"") -> A | M92: =IFERROR(VALUE(MID(D92,FIND("_",D92)+1,FIND("_",D92,FIND("_",D92)+1)-FIND("_",D92)-1)),"") -> 14 | N92: =IF(OR(C92="",M92=""),"",C92&" Item "&M92) -> Beverages Item 14 | O92: 443 | P92: =G92*Q92 -> 4.9 | Q92: =IF(K92=TRUE(),0.1,0) -> 0.1
A93: TXN_7296720 | B93: CUST_18 | C93: Patisserie | D93: Item_4_PAT | E93: 9.5 | F93: 5 | G93: 47.5 | H93: Cash | I93: Online | J93: 45547 | L93: =IFERROR(INDEX(CategoryCodes!$B$2:$B$9,MATCH(C93,CategoryCodes!$A$2:$A$9,0)),"") -> H | M93: =IFERROR(VALUE(MID(D93,FIND("_",D93)+1,FIND("_",D93,FIND("_",D93)+1)-FIND("_",D93)-1)),"") -> 4 | N93: =IF(OR(C93="",M93=""),"",C93&" Item "&M93) -> Patisserie Item 4 | O93: 51 | P93: =G93*Q93 -> 0 | Q93: =IF(K93=TRUE(),0.1,0) -> 0
A94: TXN_8414071 | B94: CUST_20 | C94: Patisserie | D94: Item_12_PAT | E94: 21.5 | F94: 9 | G94: 193.5 | H94: Cash | I94: In-store | J94: 45048 | K94: =TRUE() -> TRUE | L94: =IFERROR(INDEX(CategoryCodes!$B$2:$B$9,MATCH(C94,CategoryCodes!$A$2:$A$9,0)),"") -> H | M94: =IFERROR(VALUE(MID(D94,FIND("_",D94)+1,FIND("_",D94,FIND("_",D94)+1)-FIND("_",D94)-1)),"") -> 12 | N94: =IF(OR(C94="",M94=""),"",C94&" Item "&M94) -> Patisserie Item 12 | O94: 194 | P94: =G94*Q94 -> 19.35 | Q94: =IF(K94=TRUE(),0.1,0) -> 0.1
A95: TXN_5705131 | B95: CUST_19 | C95: Milk Products | D95: Item_4_MILK | E95: 9.5 | F95: 4 | G95: 38 | H95: Digital Wallet | I95: Online | J95: 45378 | K95: =TRUE() -> TRUE | L95: =IFERROR(INDEX(CategoryCodes!$B$2:$B$9,MATCH(C95,CategoryCodes!$A$2:$A$9,0)),"") -> G | M95: =IFERROR(VALUE(MID(D95,FIND("_",D95)+1,FIND("_",D95,FIND("_",D95)+1)-FIND("_",D95)-1)),"") -> 4 | N95: =IF(OR(C95="",M95=""),"",C95&" Item "&M95) -> Milk Products Item 4 | O95: 142 | P95: =G95*Q95 -> 3.8 | Q95: =IF(K95=TRUE(),0.1,0) -> 0.1
A96: TXN_5938028 | B96: CUST_18 | C96: Computers and electric accessories | D96: Item_7_CEA | E96: 14 | F96: 1 | G96: 14 | H96: Digital Wallet | I96: Online | J96: 44977 | K96: =TRUE() -> TRUE | L96: =IFERROR(INDEX(CategoryCodes!$B$2:$B$9,MATCH(C96,CategoryCodes!$A$2:$A$9,0)),"") -> C | M96: =IFERROR(VALUE(MID(D96,FIND("_",D96)+1,FIND("_",D96,FIND("_",D96)+1)-FIND("_",D96)-1)),"") -> 7 | N96: =IF(OR(C96="",M96=""),"",C96&" Item "&M96) -> Computers and electric accessories Item 7 | O96: 232 | P96: =G96*Q96 -> 1.4 | Q96: =IF(K96=TRUE(),0.1,0) -> 0.1
A97: TXN_1958345 | B97: CUST_08 | C97: Electric household essentials | D97: Item_4_EHE | E97: 9.5 | F97: 8 | G97: 76 | H97: Cash | I97: In-store | J97: 45471 | L97: =IFERROR(INDEX(CategoryCodes!$B$2:$B$9,MATCH(C97,CategoryCodes!$A$2:$A$9,0)),"") -> D | M97: =IFERROR(VALUE(MID(D97,FIND("_",D97)+1,FIND("_",D97,FIND("_",D97)+1)-FIND("_",D97)-1)),"") -> 4 | N97: =IF(OR(C97="",M97=""),"",C97&" Item "&M97) -> Electric household essentials Item 4 | O97: 325 | P97: =G97*Q97 -> 0 | Q97: =IF(K97=TRUE(),0.1,0) -> 0
A98: TXN_1528585 | B98: CUST_15 | C98: Electric household essentials | D98: Item_6_EHE | E98: 12.5 | F98: 1 | G98: 12.5 | H98: Credit Card | I98: In-store | J98: 45552 | L98: =IFERROR(INDEX(CategoryCodes!$B$2:$B$9,MATCH(C98,CategoryCodes!$A$2:$A$9,0)),"") -> D | M98: =IFERROR(VALUE(MID(D98,FIND("_",D98)+1,FIND("_",D98,FIND("_",D98)+1)-FIND("_",D98)-1)),"") -> 6 | N98: =IF(OR(C98="",M98=""),"",C98&" Item "&M98) -> Electric household essentials Item 6 | O98: 427 | P98: =G98*Q98 -> 0 | Q98: =IF(K98=TRUE(),0.1,0) -> 0
A99: TXN_9619859 | B99: CUST_01 | C99: Butchers | D99: Item_21_BUT | E99: 35 | F99: 4 | G99: 140 | H99: Cash | I99: In-store | J99: 45387 | K99: =FALSE() -> FALSE | L99: =IFERROR(INDEX(CategoryCodes!$B$2:$B$9,MATCH(C99,CategoryCodes!$A$2:$A$9,0)),"") -> B | M99: =IFERROR(VALUE(MID(D99,FIND("_",D99)+1,FIND("_",D99,FIND("_",D99)+1)-FIND("_",D99)-1)),"") -> 21 | N99: =IF(OR(C99="",M99=""),"",C99&" Item "&M99) -> Butchers Item 21 | O99: 186 | P99: =G99*Q99 -> 0 | Q99: =IF(K99=TRUE(),0.1,0) -> 0
A100: TXN_6158929 | B100: CUST_21 | C100: Food | D100: Item_11_FOOD | E100: 20 | F100: 6 | G100: 120 | H100: Cash | I100: Online | J100: 44590 | K100: =TRUE() -> TRUE | L100: =IFERROR(INDEX(CategoryCodes!$B$2:$B$9,MATCH(C100,CategoryCodes!$A$2:$A$9,0)),"") -> E | M100: =IFERROR(VALUE(MID(D100,FIND("_",D100)+1,FIND("_",D100,FIND("_",D100)+1)-FIND("_",D100)-1)),"") -> 11 | N100: =IF(OR(C100="",M100=""),"",C100&" Item "&M100) -> Food Item 11 | O100: 83 | P100: =G100*Q100 -> 12 | Q100: =IF(K100=TRUE(),0.1,0) -> 0.1
...

Sheet CategoryCodes
A1: Category | B1: Code
A2: Beverages | B2: A
A3: Butchers | B3: B
A4: Computers and electric accessories | B4: C
A5: Electric household essentials | B5: D
A6: Food | B6: E
A7: Furniture | B7: F
A8: Milk Products | B8: G
A9: Patisserie | B9: H
